veras/__init__.py
veras/client.py
veras/exceptions.py
veras/trace.py
veras-0.1.1.dist-info/licenses/LICENSE
veras-0.1.1.dist-info/METADATA
veras-0.1.1.dist-info/WHEEL
veras-0.1.1.dist-info/top_level.txt
veras-0.1.1.dist-info/RECORD
