Metadata-Version: 2.4
Name: veras
Version: 0.1.1
Summary: Universal agent tracing SDK for Python. Drop-in decorators to trace any agent and send to AWS.
Author-email: Veras <hi@veras.com>
License: MIT
Requires-Python: >=3.7
License-File: LICENSE
Requires-Dist: requests>=2.28.0
Dynamic: license-file
